fantasybert/__init__.py
fantasybert/core/__init__.py
fantasybert/core/callback.py
fantasybert/core/data_utils.py
fantasybert/core/logger_utils.py
fantasybert/core/loss_main.py
fantasybert/core/losses.py
fantasybert/core/metrics.py
fantasybert/core/optimization.py
fantasybert/core/tester.py
fantasybert/core/trainer.py
fantasybert/core/trainer_utils.py
fantasybert/core/utils.py
fantasybert/models/__init__.py
fantasybert/models/crf.py
fantasybert/models/model_building.py
fantasybert/models/modeling_nezha.py
fantasybert/models/modeling_unilm.py
fantasybert/models/modeling_utils.py
fantasybert/tokenization/__init__.py
fantasybert/tokenization/tokenization_base.py
fantasybert/tokenization/tokenization_utils.py
fantasybert/tokenization/tokenizers.py
fantasybert-0.1.2.dist-info/LICENSE
fantasybert-0.1.2.dist-info/METADATA
fantasybert-0.1.2.dist-info/WHEEL
fantasybert-0.1.2.dist-info/top_level.txt
fantasybert-0.1.2.dist-info/RECORD
